zcfg/__init__.py
zcfg/config.py
zcfg-2024.11.1.data/data/LICENSE
zcfg-2024.11.1.dist-info/LICENSE
zcfg-2024.11.1.dist-info/METADATA
zcfg-2024.11.1.dist-info/WHEEL
zcfg-2024.11.1.dist-info/top_level.txt
zcfg-2024.11.1.dist-info/RECORD
