Metadata-Version: 2.1
Name: zcfg
Version: 2024.11.1
Summary: Config for ini
Author: Xin-Xin Ma
License: GPL
Project-URL: Source, https://gitee.com/SIZXSN6/zcfg
License-File: LICENSE
Requires-Dist: loguru
